activestorage/__init__.py
activestorage/active.py
activestorage/config.py
activestorage/dummy_data.py
activestorage/hdf2numcodec.py
activestorage/reductionist.py
activestorage/storage.py
pyactivestorage-0.5.0.dist-info/licenses/LICENSE
pyactivestorage-0.5.0.dist-info/METADATA
pyactivestorage-0.5.0.dist-info/WHEEL
pyactivestorage-0.5.0.dist-info/top_level.txt
pyactivestorage-0.5.0.dist-info/RECORD
