Metadata-Version: 2.4
Name: PyActiveStorage
Version: 0.5.0
Summary: A Python client for Active Storage
Author-email: Valeriu Predoi <valeriu.predoi@ncas.ac.uk>, David Hassell <david.hassell@ncas.ac.uk>, Bryan Lawrence <bryan.lawrence@ncas.ac.uk>
License: BSD License, Version 3-Clause
Project-URL: Code, https://github.com/NCAS-CMS/PyActiveStorage
Project-URL: Issues, https://github.com/NCAS-CMS/PyActiveStorage/issues
Classifier: Development Status :: 5 - Production/Stable
Classifier: Environment :: Console
Classifier: Intended Audience :: Developers
Classifier: Intended Audience :: Science/Research
Classifier: License :: OSI Approved :: BSD License
Classifier: Natural Language :: English
Classifier: Operating System :: POSIX :: Linux
Classifier: Programming Language :: Python :: 3
Classifier: Programming Language :: Python :: 3.10
Classifier: Programming Language :: Python :: 3.11
Classifier: Programming Language :: Python :: 3.12
Classifier: Programming Language :: Python :: 3.13
Classifier: Programming Language :: Python :: 3.14
Classifier: Topic :: Scientific/Engineering
Classifier: Topic :: Scientific/Engineering :: Atmospheric Science
Classifier: Topic :: Scientific/Engineering :: Physics
Requires-Python: >=3.10
License-File: LICENSE
Requires-Dist: fsspec
Requires-Dist: h5netcdf
Requires-Dist: netcdf4
Requires-Dist: numcodecs>=0.12
Requires-Dist: numpy!=1.24.3
Requires-Dist: pyfive>=0.5.0
Requires-Dist: requests
Requires-Dist: s3fs>=2024.2.0
Requires-Dist: ujson
Provides-Extra: test
Requires-Dist: flake8; extra == "test"
Requires-Dist: pytest; extra == "test"
Requires-Dist: pytest-cov>=2.10.1; extra == "test"
Requires-Dist: pytest-html!=2.1.0; extra == "test"
Requires-Dist: pytest-metadata>=1.5.1; extra == "test"
Requires-Dist: pytest-xdist; extra == "test"
Requires-Dist: dask; extra == "test"
Requires-Dist: moto; extra == "test"
Provides-Extra: doc
Requires-Dist: autodocsumm; extra == "doc"
Requires-Dist: sphinx; extra == "doc"
Requires-Dist: sphinx_rtd_theme; extra == "doc"
Provides-Extra: demo
Requires-Dist: dask!=2024.8.0; extra == "demo"
Dynamic: license-file
